flywheel_gear_toolkit/__init__.py
flywheel_gear_toolkit/context/__init__.py
flywheel_gear_toolkit/context/constants.py
flywheel_gear_toolkit/context/context.py
flywheel_gear_toolkit/exceptions.py
flywheel_gear_toolkit/hpc/__init__.py
flywheel_gear_toolkit/hpc/freesurfer_utils.py
flywheel_gear_toolkit/hpc/singularity.py
flywheel_gear_toolkit/interfaces/__init__.py
flywheel_gear_toolkit/interfaces/command_line.py
flywheel_gear_toolkit/interfaces/engine_metadata.json
flywheel_gear_toolkit/interfaces/nipype.py
flywheel_gear_toolkit/licenses/__init__.py
flywheel_gear_toolkit/licenses/freesurfer.py
flywheel_gear_toolkit/logging/__init__.py
flywheel_gear_toolkit/logging/defaults/debug.json
flywheel_gear_toolkit/logging/defaults/info.json
flywheel_gear_toolkit/testing/__init__.py
flywheel_gear_toolkit/testing/files.py
flywheel_gear_toolkit/testing/gears.py
flywheel_gear_toolkit/testing/hierarchy.py
flywheel_gear_toolkit/testing/sdk.py
flywheel_gear_toolkit/testing/utils.py
flywheel_gear_toolkit/utils/__init__.py
flywheel_gear_toolkit/utils/config.py
flywheel_gear_toolkit/utils/curator.py
flywheel_gear_toolkit/utils/datatypes.py
flywheel_gear_toolkit/utils/decorators.py
flywheel_gear_toolkit/utils/file.py
flywheel_gear_toolkit/utils/manifest.py
flywheel_gear_toolkit/utils/metadata.py
flywheel_gear_toolkit/utils/reporters.py
flywheel_gear_toolkit/utils/walker.py
flywheel_gear_toolkit/utils/zip_tools.py
flywheel_gear_toolkit-0.6.22.dist-info/LICENSE
flywheel_gear_toolkit-0.6.22.dist-info/METADATA
flywheel_gear_toolkit-0.6.22.dist-info/WHEEL
flywheel_gear_toolkit-0.6.22.dist-info/entry_points.txt
flywheel_gear_toolkit-0.6.22.dist-info/RECORD
