Metadata-Version: 2.3
Name: flywheel-gear-toolkit
Version: 0.6.22
Summary: Tooling for developing Flywheel gears
License: MIT
Author: Flywheel
Author-email: support@flywheel.io
Requires-Python: >=3.9,<4.0
Classifier: License :: OSI Approved :: MIT License
Classifier: Programming Language :: Python :: 3
Classifier: Programming Language :: Python :: 3.9
Classifier: Programming Language :: Python :: 3.10
Classifier: Programming Language :: Python :: 3.11
Classifier: Programming Language :: Python :: 3.12
Classifier: Programming Language :: Python :: 3.13
Provides-Extra: all
Provides-Extra: dicom
Provides-Extra: fw-file
Provides-Extra: nipype
Provides-Extra: numpy
Provides-Extra: sdk
Requires-Dist: backports.zoneinfo (>=0,<1) ; python_version == "3.8"
Requires-Dist: dotty-dict (>=1.2.1,<2.0.0)
Requires-Dist: flywheel-bids (>=1.0.8,<2.0.0) ; (python_full_version >= "3.7.1" and python_full_version < "4.0.0") and (extra == "all" or extra == "sdk")
Requires-Dist: flywheel-gears (>=0,<1)
Requires-Dist: flywheel-sdk (>=14.2.0) ; extra == "all" or extra == "sdk"
Requires-Dist: fw-file (>=2) ; extra == "all" or extra == "dicom" or extra == "fw-file"
Requires-Dist: fw-gear (==0.1.3)
Requires-Dist: jsonschema (>=4.0.0,<5.0.0)
Requires-Dist: nibabel (>=5.1.0,<6.0.0) ; extra == "all" or extra == "dicom" or extra == "nipype"
Requires-Dist: nipype (>=1.6,<2.0) ; extra == "all" or extra == "nipype"
Requires-Dist: numpy (>=1.26.0) ; (python_version >= "3.9" and python_version < "4.0") and (extra == "all" or extra == "numpy")
Project-URL: Documentation, https://gear-toolkit.readthedocs.io/en/latest/
Project-URL: Repository, https://gitlab.com/flywheel-io/public/gear-toolkit
